quantum_progress_bar/__init__.py
quantum_progress_bar/quantum_progress_bar.py
quantum_progress_bar-0.1.1.dist-info/METADATA
quantum_progress_bar-0.1.1.dist-info/WHEEL
quantum_progress_bar-0.1.1.dist-info/licenses/LICENSE
quantum_progress_bar-0.1.1.dist-info/RECORD
