Metadata-Version: 2.4
Name: quantum-progress-bar
Version: 0.1.1
Summary: The Ultimate Quantum Progress Bar
Project-URL: Repository, https://github.com/FlatBone/quantum-progress-bar.git
License-File: LICENSE
Requires-Python: >=3.10
